<?xml version='1.0' encoding='utf-8'?>
<gamesList><games><game>
			<appID>1610410</appID>
			<name>MR 333</name>
			<logo>https://cdn.cloudflare.steamstatic.com/steam/apps/1610410/capsule_184x69.jpg?t=1705138727</logo>
			<storeLink>https://steamcommunity.com/app/1610410</storeLink>
		</game>
		<game>
			<appID>1649480</appID>
			<name>Mrs. Fantastic's Freaky Figurine Shop</name>
			<logo>https://cdn.cloudflare.steamstatic.com/steam/apps/1649480/capsule_184x69.jpg?t=1678980859</logo>
			<storeLink>https://steamcommunity.com/app/1649480</storeLink>
		</game>
		<game>
			<appID>1473660</appID>
			<name>Mrs. Santa's Gift Hunt</name>
			<logo>https://cdn.cloudflare.steamstatic.com/steam/apps/1473660/capsule_184x69.jpg?t=1640424772</logo>
			<storeLink>https://steamcommunity.com/app/1473660</storeLink>
			<statsLink>https://steamcommunity.com/id/impizzaman/stats/1473660</statsLink>
			<globalStatsLink>https://steamcommunity.com/stats/1473660/achievements/</globalStatsLink>
		</game>
		<game>
			<appID>1625450</appID>
			<name>Muck</name>
			<logo>https://cdn.cloudflare.steamstatic.com/steam/apps/1625450/capsule_184x69.jpg?t=1625163481</logo>
			<storeLink>https://steamcommunity.com/app/1625450</storeLink>
			<statsLink>https://steamcommunity.com/id/impizzaman/stats/1625450</statsLink>
			<globalStatsLink>https://steamcommunity.com/stats/1625450/achievements/</globalStatsLink>
		</game>
		<game>
			<appID>863170</appID>
			<name>Muerte's Arena</name>
			<logo>https://cdn.cloudflare.steamstatic.com/steam/apps/863170/capsule_184x69.jpg?t=1572312906</logo>
			<storeLink>https://steamcommunity.com/app/863170</storeLink>
		</game>
		<game>
			<appID>874240</appID>
			<name>MU Legend</name>
			<logo>https://cdn.cloudflare.steamstatic.com/steam/apps/874240/capsule_184x69.jpg?t=1690492793</logo>
			<storeLink>https://steamcommunity.com/app/874240</storeLink>
		</game>
		<game>
			<appID>931260</appID>
			<name>Multibombers</name>
			<logo>https://cdn.cloudflare.steamstatic.com/steam/apps/931260/capsule_184x69.jpg?t=1570125794</logo>
			<storeLink>https://steamcommunity.com/app/931260</storeLink>
			<statsLink>https://steamcommunity.com/id/impizzaman/stats/931260</statsLink>
			<globalStatsLink>https://steamcommunity.com/stats/931260/achievements/</globalStatsLink>
		</game>
		<game>
			<appID>1708090</appID>
			<name>Multiplayer High-Res Textures</name>
			<logo>https://cdn.cloudflare.steamstatic.com/steam/apps/1708090/capsule_184x69.jpg</logo>
			<storeLink>https://steamcommunity.com/app/1708090</storeLink>
		</game>
		<game>
			<appID>704340</appID>
			<name>Multiplayer Mini-Golf Game Source Code (Full Project)</name>
			<logo>https://cdn.cloudflare.steamstatic.com/steam/apps/704340/capsule_184x69.jpg?t=1508249420</logo>
			<storeLink>https://steamcommunity.com/app/704340</storeLink>
		</game>
		<game>
			<appID>1473940</appID>
			<name>MultiVerse</name>
			<logo>https://cdn.cloudflare.steamstatic.com/steam/apps/1473940/capsule_184x69.jpg?t=1647690045</logo>
			<storeLink>https://steamcommunity.com/app/1473940</storeLink>
		</game>
		<game>
			<appID>2161190</appID>
			<name>Multiverse Mercenaries</name>
			<logo>https://cdn.cloudflare.steamstatic.com/steam/apps/2161190/capsule_184x69.jpg?t=1665763236</logo>
			<storeLink>https://steamcommunity.com/app/2161190</storeLink>
		</game>
		<game>
			<appID>1818750</appID>
			<name>MultiVersus</name>
			<logo>https://cdn.cloudflare.steamstatic.com/steam/apps/1818750/capsule_184x69.jpg?t=1680624056</logo>
			<storeLink>https://steamcommunity.com/app/1818750</storeLink>
			<statsLink>https://steamcommunity.com/id/impizzaman/stats/1818750</statsLink>
			<globalStatsLink>https://steamcommunity.com/stats/1818750/achievements/</globalStatsLink>
		</game>
		<game>
			<appID>871490</appID>
			<name>Munx VR</name>
			<logo>https://cdn.cloudflare.steamstatic.com/steam/apps/871490/capsule_184x69.jpg?t=1610783903</logo>
			<storeLink>https://steamcommunity.com/app/871490</storeLink>
		</game>
		<game>
			<appID>1068520</appID>
			<name>Muppy The Bunny : The Danger of Wishes</name>
			<logo>https://cdn.cloudflare.steamstatic.com/steam/apps/1068520/capsule_184x69.jpg?t=1597973174</logo>
			<storeLink>https://steamcommunity.com/app/1068520</storeLink>
		</game>
		<game>
			<appID>2129000</appID>
			<name>Murders at Tealwoods Manor</name>
			<logo>https://cdn.cloudflare.steamstatic.com/steam/apps/2129000/capsule_184x69.jpg?t=1682868262</logo>
			<storeLink>https://steamcommunity.com/app/2129000</storeLink>
			<statsLink>https://steamcommunity.com/id/impizzaman/stats/2129000</statsLink>
			<globalStatsLink>https://steamcommunity.com/stats/2129000/achievements/</globalStatsLink>
		</game>
		<game>
			<appID>1061150</appID>
			<name>Muscle Magic</name>
			<logo>https://cdn.cloudflare.steamstatic.com/steam/apps/1061150/capsule_184x69.jpg?t=1562103852</logo>
			<storeLink>https://steamcommunity.com/app/1061150</storeLink>
			<statsLink>https://steamcommunity.com/id/impizzaman/stats/1061150</statsLink>
			<globalStatsLink>https://steamcommunity.com/stats/1061150/achievements/</globalStatsLink>
		</game>
		<game>
			<appID>1879340</appID>
			<name>MuseSwipr</name>
			<logo>https://cdn.cloudflare.steamstatic.com/steam/apps/1879340/capsule_184x69.jpg?t=1704450025</logo>
			<storeLink>https://steamcommunity.com/app/1879340</storeLink>
			<statsLink>https://steamcommunity.com/id/impizzaman/stats/1879340</statsLink>
			<globalStatsLink>https://steamcommunity.com/stats/1879340/achievements/</globalStatsLink>
		</game>
		<game>
			<appID>613900</appID>
			<name>Museum of Other Realities</name>
			<logo>https://cdn.cloudflare.steamstatic.com/steam/apps/613900/capsule_184x69.jpg?t=1638911779</logo>
			<storeLink>https://steamcommunity.com/app/613900</storeLink>
		</game>
		<game>
			<appID>870890</appID>
			<name>Museum of Symmetry</name>
			<logo>https://cdn.cloudflare.steamstatic.com/steam/apps/870890/capsule_184x69.jpg?t=1701786388</logo>
			<storeLink>https://steamcommunity.com/app/870890</storeLink>
		</game>
		<game>
			<appID>1071120</appID>
			<name>Mushroom Cats</name>
			<logo>https://cdn.cloudflare.steamstatic.com/steam/apps/1071120/capsule_184x69.jpg?t=1646565787</logo>
			<storeLink>https://steamcommunity.com/app/1071120</storeLink>
			<statsLink>https://steamcommunity.com/id/impizzaman/stats/1071120</statsLink>
			<globalStatsLink>https://steamcommunity.com/stats/1071120/achievements/</globalStatsLink>
		</game>
		<game>
			<appID>2077530</appID>
			<name>Mushroom Musical</name>
			<logo>https://cdn.cloudflare.steamstatic.com/steam/apps/2077530/capsule_184x69.jpg?t=1680993350</logo>
			<storeLink>https://steamcommunity.com/app/2077530</storeLink>
		</game>
		<game>
			<appID>1772820</appID>
			<name>Mushy</name>
			<logo>https://cdn.cloudflare.steamstatic.com/steam/apps/1772820/capsule_184x69.jpg?t=1655993857</logo>
			<storeLink>https://steamcommunity.com/app/1772820</storeLink>
		</game>
		<game>
			<appID>818620</appID>
			<name>Music Boy 3D</name>
			<logo>https://cdn.cloudflare.steamstatic.com/steam/apps/818620/capsule_184x69.jpg?t=1549047684</logo>
			<storeLink>https://steamcommunity.com/app/818620</storeLink>
			<statsLink>https://steamcommunity.com/id/impizzaman/stats/818620</statsLink>
			<globalStatsLink>https://steamcommunity.com/stats/818620/achievements/</globalStatsLink>
		</game>
		<game>
			<appID>1630000</appID>
			<name>Musicle</name>
			<logo>https://cdn.cloudflare.steamstatic.com/steam/apps/1630000/capsule_184x69.jpg?t=1629356907</logo>
			<storeLink>https://steamcommunity.com/app/1630000</storeLink>
		</game>
		<game>
			<appID>1390680</appID>
			<name>Music Maker Free Steam Edition</name>
			<logo>https://cdn.cloudflare.steamstatic.com/steam/apps/1390680/capsule_184x69.jpg?t=1684166261</logo>
			<storeLink>https://steamcommunity.com/app/1390680</storeLink>
		</game>
		<game>
			<appID>906810</appID>
			<name>Music Maker Steam Edition</name>
			<logo>https://cdn.cloudflare.steamstatic.com/steam/apps/906810/capsule_184x69.jpg?t=1684166350</logo>
			<storeLink>https://steamcommunity.com/app/906810</storeLink>
		</game>
		<game>
			<appID>2273470</appID>
			<name>Music Store Simulator Prologue</name>
			<logo>https://cdn.cloudflare.steamstatic.com/steam/apps/2273470/capsule_184x69.jpg?t=1704406371</logo>
			<storeLink>https://steamcommunity.com/app/2273470</storeLink>
			<statsLink>https://steamcommunity.com/id/impizzaman/stats/2273470</statsLink>
			<globalStatsLink>https://steamcommunity.com/stats/2273470/achievements/</globalStatsLink>
		</game>
		<game>
			<appID>1308030</appID>
			<name>Music To Go POSTAL By</name>
			<logo>https://cdn.cloudflare.steamstatic.com/steam/apps/1308030/capsule_184x69.jpg?t=1700053606</logo>
			<storeLink>https://steamcommunity.com/app/1308030</storeLink>
		</game>
		<game>
			<appID>2160160</appID>
			<name>Music to Go POSTAL By Volume 2: POSTAL 4 Edition</name>
			<logo>https://cdn.cloudflare.steamstatic.com/steam/apps/2160160/capsule_184x69.jpg?t=1664287637</logo>
			<storeLink>https://steamcommunity.com/app/2160160</storeLink>
		</game>
		<game>
			<appID>1283690</appID>
			<name>Music_is_the_Language</name>
			<logo>https://cdn.cloudflare.steamstatic.com/steam/apps/1283690/capsule_184x69.jpg?t=1652842313</logo>
			<storeLink>https://steamcommunity.com/app/1283690</storeLink>
		</game>
		<game>
			<appID>2138570</appID>
			<name>Mutants: Genesis</name>
			<logo>https://cdn.cloudflare.steamstatic.com/steam/apps/2138570/capsule_184x69.jpg?t=1691768786</logo>
			<storeLink>https://steamcommunity.com/app/2138570</storeLink>
		</game>
		<game>
			<appID>860330</appID>
			<name>Mutation Mayhem</name>
			<logo>https://cdn.cloudflare.steamstatic.com/steam/apps/860330/capsule_184x69.jpg?t=1528930528</logo>
			<storeLink>https://steamcommunity.com/app/860330</storeLink>
		</game>
		<game>
			<appID>1706450</appID>
			<name>MVR</name>
			<logo>https://cdn.cloudflare.steamstatic.com/steam/apps/1706450/capsule_184x69.jpg?t=1645310014</logo>
			<storeLink>https://steamcommunity.com/app/1706450</storeLink>
		</game>
		<game>
			<appID>1255660</appID>
			<name>Mya of the Desert</name>
			<logo>https://cdn.cloudflare.steamstatic.com/steam/apps/1255660/capsule_184x69.jpg?t=1590475016</logo>
			<storeLink>https://steamcommunity.com/app/1255660</storeLink>
			<statsLink>https://steamcommunity.com/id/impizzaman/stats/1255660</statsLink>
			<globalStatsLink>https://steamcommunity.com/stats/1255660/achievements/</globalStatsLink>
		</game>
		<game>
			<appID>1506600</appID>
			<name>My boss is weird</name>
			<logo>https://cdn.cloudflare.steamstatic.com/steam/apps/1506600/capsule_184x69.jpg?t=1696267003</logo>
			<storeLink>https://steamcommunity.com/app/1506600</storeLink>
			<statsLink>https://steamcommunity.com/id/impizzaman/stats/1506600</statsLink>
			<globalStatsLink>https://steamcommunity.com/stats/1506600/achievements/</globalStatsLink>
		</game>
		<game>
			<appID>1641020</appID>
			<name>my brother lives in a canyon</name>
			<logo>https://cdn.cloudflare.steamstatic.com/steam/apps/1641020/capsule_184x69.jpg?t=1656705273</logo>
			<storeLink>https://steamcommunity.com/app/1641020</storeLink>
			<statsLink>https://steamcommunity.com/id/impizzaman/stats/1641020</statsLink>
			<globalStatsLink>https://steamcommunity.com/stats/1641020/achievements/</globalStatsLink>
		</game>
		<game>
			<appID>2546640</appID>
			<name>My Camp of Memories: Episode 1</name>
			<logo>https://cdn.cloudflare.steamstatic.com/steam/apps/2546640/capsule_184x69.jpg?t=1703937338</logo>
			<storeLink>https://steamcommunity.com/app/2546640</storeLink>
		</game>
		<game>
			<appID>1582890</appID>
			<name>My Catgirl Maid Thinks She Runs the Place</name>
			<logo>https://cdn.cloudflare.steamstatic.com/steam/apps/1582890/capsule_184x69.jpg?t=1627151135</logo>
			<storeLink>https://steamcommunity.com/app/1582890</storeLink>
			<statsLink>https://steamcommunity.com/id/impizzaman/stats/1582890</statsLink>
			<globalStatsLink>https://steamcommunity.com/stats/1582890/achievements/</globalStatsLink>
		</game>
		<game>
			<appID>2128650</appID>
			<name>Mycorrhiza Soundtrack</name>
			<logo>https://cdn.cloudflare.steamstatic.com/steam/apps/2128650/capsule_184x69.jpg?t=1664524198</logo>
			<storeLink>https://steamcommunity.com/app/2128650</storeLink>
		</game>
		<game>
			<appID>2077870</appID>
			<name>My Dad Left Me</name>
			<logo>https://cdn.cloudflare.steamstatic.com/steam/apps/2077870/capsule_184x69.jpg?t=1707117603</logo>
			<storeLink>https://steamcommunity.com/app/2077870</storeLink>
			<statsLink>https://steamcommunity.com/id/impizzaman/stats/2077870</statsLink>
			<globalStatsLink>https://steamcommunity.com/stats/2077870/achievements/</globalStatsLink>
		</game>
		<game>
			<appID>1049880</appID>
			<name>My Free Farm</name>
			<logo>https://cdn.cloudflare.steamstatic.com/steam/apps/1049880/capsule_184x69.jpg?t=1667823012</logo>
			<storeLink>https://steamcommunity.com/app/1049880</storeLink>
		</game>
		<game>
			<appID>799240</appID>
			<name>My Free Farm 2</name>
			<logo>https://cdn.cloudflare.steamstatic.com/steam/apps/799240/capsule_184x69.jpg?t=1667822971</logo>
			<storeLink>https://steamcommunity.com/app/799240</storeLink>
			<statsLink>https://steamcommunity.com/id/impizzaman/stats/799240</statsLink>
			<globalStatsLink>https://steamcommunity.com/stats/799240/achievements/</globalStatsLink>
		</game>
		<game>
			<appID>1215090</appID>
			<name>My Friend is a Raven</name>
			<logo>https://cdn.cloudflare.steamstatic.com/steam/apps/1215090/capsule_184x69.jpg?t=1671315071</logo>
			<storeLink>https://steamcommunity.com/app/1215090</storeLink>
		</game>
		<game>
			<appID>1251690</appID>
			<name>My Hole is a Mouth of Dirt</name>
			<logo>https://cdn.cloudflare.steamstatic.com/steam/apps/1251690/capsule_184x69.jpg?t=1586836370</logo>
			<storeLink>https://steamcommunity.com/app/1251690</storeLink>
		</game>
		<game>
			<appID>1742530</appID>
			<name>My journey to your world</name>
			<logo>https://cdn.cloudflare.steamstatic.com/steam/apps/1742530/capsule_184x69.jpg?t=1644119559</logo>
			<storeLink>https://steamcommunity.com/app/1742530</storeLink>
			<statsLink>https://steamcommunity.com/id/impizzaman/stats/1742530</statsLink>
			<globalStatsLink>https://steamcommunity.com/stats/1742530/achievements/</globalStatsLink>
		</game>
		<game>
			<appID>1131540</appID>
			<name>My Light In The Dark</name>
			<logo>https://cdn.cloudflare.steamstatic.com/steam/apps/1131540/capsule_184x69.jpg?t=1625319202</logo>
			<storeLink>https://steamcommunity.com/app/1131540</storeLink>
		</game>
		<game>
			<appID>789100</appID>
			<name>My Little Farmies</name>
			<logo>https://cdn.cloudflare.steamstatic.com/steam/apps/789100/capsule_184x69.jpg?t=1667822850</logo>
			<storeLink>https://steamcommunity.com/app/789100</storeLink>
			<statsLink>https://steamcommunity.com/id/impizzaman/stats/789100</statsLink>
			<globalStatsLink>https://steamcommunity.com/stats/789100/achievements/</globalStatsLink>
		</game>
		<game>
			<appID>2200390</appID>
			<name>My Little Miniatures</name>
			<logo>https://cdn.cloudflare.steamstatic.com/steam/apps/2200390/capsule_184x69.jpg?t=1680860951</logo>
			<storeLink>https://steamcommunity.com/app/2200390</storeLink>
			<statsLink>https://steamcommunity.com/id/impizzaman/stats/2200390</statsLink>
			<globalStatsLink>https://steamcommunity.com/stats/2200390/achievements/</globalStatsLink>
		</game>
		<game>
			<appID>1964380</appID>
			<name>My little sister: Prologue</name>
			<logo>https://cdn.cloudflare.steamstatic.com/steam/apps/1964380/capsule_184x69.jpg?t=1652430265</logo>
			<storeLink>https://steamcommunity.com/app/1964380</storeLink>
		</game>
		<game>
			<appID>2129970</appID>
			<name>My Loving Wife</name>
			<logo>https://cdn.cloudflare.steamstatic.com/steam/apps/2129970/capsule_184x69.jpg?t=1670364448</logo>
			<storeLink>https://steamcommunity.com/app/2129970</storeLink>
			<statsLink>https://steamcommunity.com/id/impizzaman/stats/2129970</statsLink>
			<globalStatsLink>https://steamcommunity.com/stats/2129970/achievements/</globalStatsLink>
		</game>
		</games></gamesList>