<?xml version='1.0' encoding='utf-8'?>
<gamesList><games><game>
			<appID>681950</appID>
			<name>AddForce</name>
			<logo>https://cdn.cloudflare.steamstatic.com/steam/apps/681950/capsule_184x69.jpg?t=1605104594</logo>
			<storeLink>https://steamcommunity.com/app/681950</storeLink>
		</game>
		<game>
			<appID>2394810</appID>
			<name>ADDRESS1</name>
			<logo>https://cdn.cloudflare.steamstatic.com/steam/apps/2394810/capsule_184x69.jpg?t=1694092858</logo>
			<storeLink>https://steamcommunity.com/app/2394810</storeLink>
			<statsLink>https://steamcommunity.com/id/impizzaman/stats/2394810</statsLink>
			<globalStatsLink>https://steamcommunity.com/stats/2394810/achievements/</globalStatsLink>
		</game>
		<game>
			<appID>1199560</appID>
			<name>Adrift Arena</name>
			<logo>https://cdn.cloudflare.steamstatic.com/steam/apps/1199560/capsule_184x69.jpg?t=1634560432</logo>
			<storeLink>https://steamcommunity.com/app/1199560</storeLink>
		</game>
		<game>
			<appID>2271810</appID>
			<name>ADT Pilot 01</name>
			<logo>https://cdn.cloudflare.steamstatic.com/steam/apps/2271810/capsule_184x69.jpg?t=1678595914</logo>
			<storeLink>https://steamcommunity.com/app/2271810</storeLink>
		</game>
		<game>
			<appID>2007420</appID>
			<name>Advanced Map Generation</name>
			<logo>https://cdn.cloudflare.steamstatic.com/steam/apps/2007420/capsule_184x69.jpg?t=1657072237</logo>
			<storeLink>https://steamcommunity.com/app/2007420</storeLink>
		</game>
		<game>
			<appID>371370</appID>
			<name>Advent</name>
			<logo>https://cdn.cloudflare.steamstatic.com/steam/apps/371370/capsule_184x69.jpg?t=1540846039</logo>
			<storeLink>https://steamcommunity.com/app/371370</storeLink>
		</game>
		<game>
			<appID>2096130</appID>
			<name>Adventure's Calling</name>
			<logo>https://cdn.cloudflare.steamstatic.com/steam/apps/2096130/capsule_184x69.jpg?t=1677822910</logo>
			<storeLink>https://steamcommunity.com/app/2096130</storeLink>
		</game>
		<game>
			<appID>1207380</appID>
			<name>Adventure Boy Jailbreak</name>
			<logo>https://cdn.cloudflare.steamstatic.com/steam/apps/1207380/capsule_184x69.jpg?t=1616852845</logo>
			<storeLink>https://steamcommunity.com/app/1207380</storeLink>
		</game>
		<game>
			<appID>1040430</appID>
			<name>Adventure Climb VR</name>
			<logo>https://cdn.cloudflare.steamstatic.com/steam/apps/1040430/capsule_184x69.jpg?t=1683573423</logo>
			<storeLink>https://steamcommunity.com/app/1040430</storeLink>
			<statsLink>https://steamcommunity.com/id/impizzaman/stats/1040430</statsLink>
			<globalStatsLink>https://steamcommunity.com/stats/1040430/achievements/</globalStatsLink>
		</game>
		<game>
			<appID>624890</appID>
			<name>Adventure Craft</name>
			<logo>https://cdn.cloudflare.steamstatic.com/steam/apps/624890/capsule_184x69.jpg?t=1610763767</logo>
			<storeLink>https://steamcommunity.com/app/624890</storeLink>
		</game>
		<game>
			<appID>1141020</appID>
			<name>Adventure Escape Mysteries</name>
			<logo>https://cdn.cloudflare.steamstatic.com/steam/apps/1141020/capsule_184x69.jpg?t=1703197908</logo>
			<storeLink>https://steamcommunity.com/app/1141020</storeLink>
			<statsLink>https://steamcommunity.com/id/impizzaman/stats/1141020</statsLink>
			<globalStatsLink>https://steamcommunity.com/stats/1141020/achievements/</globalStatsLink>
		</game>
		<game>
			<appID>1269600</appID>
			<name>Adventure Field™ 3 Definitive Edition</name>
			<logo>https://cdn.cloudflare.steamstatic.com/steam/apps/1269600/capsule_184x69.jpg?t=1686831702</logo>
			<storeLink>https://steamcommunity.com/app/1269600</storeLink>
			<statsLink>https://steamcommunity.com/id/impizzaman/stats/1269600</statsLink>
			<globalStatsLink>https://steamcommunity.com/stats/1269600/achievements/</globalStatsLink>
		</game>
		<game>
			<appID>1907170</appID>
			<name>Adventure in My Head</name>
			<logo>https://cdn.cloudflare.steamstatic.com/steam/apps/1907170/capsule_184x69.jpg?t=1655360549</logo>
			<storeLink>https://steamcommunity.com/app/1907170</storeLink>
		</game>
		<game>
			<appID>1805310</appID>
			<name>Adventure of Leek</name>
			<logo>https://cdn.cloudflare.steamstatic.com/steam/apps/1805310/capsule_184x69.jpg?t=1645964072</logo>
			<storeLink>https://steamcommunity.com/app/1805310</storeLink>
			<statsLink>https://steamcommunity.com/id/impizzaman/stats/1805310</statsLink>
			<globalStatsLink>https://steamcommunity.com/stats/1805310/achievements/</globalStatsLink>
		</game>
		<game>
			<appID>1379590</appID>
			<name>Adventures in Morality: An Interactive Case Study</name>
			<logo>https://cdn.cloudflare.steamstatic.com/steam/apps/1379590/capsule_184x69.jpg?t=1597424904</logo>
			<storeLink>https://steamcommunity.com/app/1379590</storeLink>
		</game>
		<game>
			<appID>1146500</appID>
			<name>Adventure Slime</name>
			<logo>https://cdn.cloudflare.steamstatic.com/steam/apps/1146500/capsule_184x69.jpg?t=1670242321</logo>
			<storeLink>https://steamcommunity.com/app/1146500</storeLink>
		</game>
		<game>
			<appID>2089340</appID>
			<name>Adventures of Quin85</name>
			<logo>https://cdn.cloudflare.steamstatic.com/steam/apps/2089340/capsule_184x69.jpg?t=1685381698</logo>
			<storeLink>https://steamcommunity.com/app/2089340</storeLink>
			<statsLink>https://steamcommunity.com/id/impizzaman/stats/2089340</statsLink>
			<globalStatsLink>https://steamcommunity.com/stats/2089340/achievements/</globalStatsLink>
		</game>
		<game>
			<appID>1514100</appID>
			<name>Adventure War : Battlefield</name>
			<logo>https://cdn.cloudflare.steamstatic.com/steam/apps/1514100/capsule_184x69.jpg?t=1644191383</logo>
			<storeLink>https://steamcommunity.com/app/1514100</storeLink>
		</game>
		<game>
			<appID>2115820</appID>
			<name>adventure_with_firefly</name>
			<logo>https://cdn.cloudflare.steamstatic.com/steam/apps/2115820/capsule_184x69.jpg?t=1664809546</logo>
			<storeLink>https://steamcommunity.com/app/2115820</storeLink>
		</game>
		<game>
			<appID>1131590</appID>
			<name>Aegis Online</name>
			<logo>https://cdn.cloudflare.steamstatic.com/steam/apps/1131590/capsule_184x69.jpg?t=1604374668</logo>
			<storeLink>https://steamcommunity.com/app/1131590</storeLink>
		</game>
		<game>
			<appID>885730</appID>
			<name>Aerial Guardian</name>
			<logo>https://cdn.cloudflare.steamstatic.com/steam/apps/885730/capsule_184x69.jpg?t=1532404014</logo>
			<storeLink>https://steamcommunity.com/app/885730</storeLink>
		</game>
		<game>
			<appID>832510</appID>
			<name>AeroChopper</name>
			<logo>https://cdn.cloudflare.steamstatic.com/steam/apps/832510/capsule_184x69.jpg?t=1525053918</logo>
			<storeLink>https://steamcommunity.com/app/832510</storeLink>
		</game>
		<game>
			<appID>929740</appID>
			<name>Aeronaut</name>
			<logo>https://cdn.cloudflare.steamstatic.com/steam/apps/929740/capsule_184x69.jpg?t=1568314406</logo>
			<storeLink>https://steamcommunity.com/app/929740</storeLink>
		</game>
		<game>
			<appID>1943610</appID>
			<name>Aero Tales Online: The World - Anime MMORPG</name>
			<logo>https://cdn.cloudflare.steamstatic.com/steam/apps/1943610/capsule_184x69.jpg?t=1707532938</logo>
			<storeLink>https://steamcommunity.com/app/1943610</storeLink>
			<statsLink>https://steamcommunity.com/id/impizzaman/stats/1943610</statsLink>
			<globalStatsLink>https://steamcommunity.com/stats/1943610/achievements/</globalStatsLink>
		</game>
		<game>
			<appID>2163710</appID>
			<name>Aevumblade Chronicles</name>
			<logo>https://cdn.cloudflare.steamstatic.com/steam/apps/2163710/capsule_184x69.jpg?t=1679713041</logo>
			<storeLink>https://steamcommunity.com/app/2163710</storeLink>
		</game>
		<game>
			<appID>567040</appID>
			<name>AffordaGolf Online</name>
			<logo>https://cdn.cloudflare.steamstatic.com/steam/apps/567040/capsule_184x69.jpg?t=1591382803</logo>
			<storeLink>https://steamcommunity.com/app/567040</storeLink>
			<statsLink>https://steamcommunity.com/id/impizzaman/stats/567040</statsLink>
			<globalStatsLink>https://steamcommunity.com/stats/567040/achievements/</globalStatsLink>
		</game>
		<game>
			<appID>1363160</appID>
			<name>A Field of Flowers and Stars</name>
			<logo>https://cdn.cloudflare.steamstatic.com/steam/apps/1363160/capsule_184x69.jpg?t=1631647256</logo>
			<storeLink>https://steamcommunity.com/app/1363160</storeLink>
		</game>
		<game>
			<appID>1739970</appID>
			<name>AFK Summoner</name>
			<logo>https://cdn.cloudflare.steamstatic.com/steam/apps/1739970/capsule_184x69.jpg?t=1694521818</logo>
			<storeLink>https://steamcommunity.com/app/1739970</storeLink>
		</game>
		<game>
			<appID>1447680</appID>
			<name>A Forgetful Loop Soundtrack</name>
			<logo>https://cdn.cloudflare.steamstatic.com/steam/apps/1447680/capsule_184x69.jpg?t=1604689119</logo>
			<storeLink>https://steamcommunity.com/app/1447680</storeLink>
		</game>
		<game>
			<appID>1201220</appID>
			<name>Afterbern Democralypse</name>
			<logo>https://cdn.cloudflare.steamstatic.com/steam/apps/1201220/capsule_184x69.jpg?t=1589303865</logo>
			<storeLink>https://steamcommunity.com/app/1201220</storeLink>
		</game>
		<game>
			<appID>1794250</appID>
			<name>After Dark VR</name>
			<logo>https://cdn.cloudflare.steamstatic.com/steam/apps/1794250/capsule_184x69.jpg?t=1691496125</logo>
			<storeLink>https://steamcommunity.com/app/1794250</storeLink>
		</game>
		<game>
			<appID>989040</appID>
			<name>After Hours</name>
			<logo>https://cdn.cloudflare.steamstatic.com/steam/apps/989040/capsule_184x69.jpg?t=1575234254</logo>
			<storeLink>https://steamcommunity.com/app/989040</storeLink>
			<statsLink>https://steamcommunity.com/id/impizzaman/stats/989040</statsLink>
			<globalStatsLink>https://steamcommunity.com/stats/989040/achievements/</globalStatsLink>
		</game>
		<game>
			<appID>1884540</appID>
			<name>AfterHours</name>
			<logo>https://cdn.cloudflare.steamstatic.com/steam/apps/1884540/capsule_184x69.jpg?t=1645213832</logo>
			<storeLink>https://steamcommunity.com/app/1884540</storeLink>
		</game>
		<game>
			<appID>550240</appID>
			<name>After Life - Story of a Father</name>
			<logo>https://cdn.cloudflare.steamstatic.com/steam/apps/550240/capsule_184x69.jpg?t=1553520642</logo>
			<storeLink>https://steamcommunity.com/app/550240</storeLink>
		</game>
		<game>
			<appID>1138010</appID>
			<name>Aftermoor</name>
			<logo>https://cdn.cloudflare.steamstatic.com/steam/apps/1138010/capsule_184x69.jpg?t=1670242398</logo>
			<storeLink>https://steamcommunity.com/app/1138010</storeLink>
		</game>
		<game>
			<appID>1639890</appID>
			<name>After School Murder Club!!</name>
			<logo>https://cdn.cloudflare.steamstatic.com/steam/apps/1639890/capsule_184x69.jpg?t=1662577279</logo>
			<storeLink>https://steamcommunity.com/app/1639890</storeLink>
			<statsLink>https://steamcommunity.com/id/impizzaman/stats/1639890</statsLink>
			<globalStatsLink>https://steamcommunity.com/stats/1639890/achievements/</globalStatsLink>
		</game>
		<game>
			<appID>2027360</appID>
			<name>After the Inferno</name>
			<logo>https://cdn.cloudflare.steamstatic.com/steam/apps/2027360/capsule_184x69.jpg?t=1671219873</logo>
			<storeLink>https://steamcommunity.com/app/2027360</storeLink>
		</game>
		<game>
			<appID>1816840</appID>
			<name>Afterthought Soundtrack Disc 1-4</name>
			<logo>https://cdn.cloudflare.steamstatic.com/steam/apps/1816840/capsule_184x69.jpg?t=1677854878</logo>
			<storeLink>https://steamcommunity.com/app/1816840</storeLink>
		</game>
		<game>
			<appID>1263610</appID>
			<name>AftLife -Girl and Cats, and Lost world-</name>
			<logo>https://cdn.cloudflare.steamstatic.com/steam/apps/1263610/capsule_184x69.jpg?t=1585137619</logo>
			<storeLink>https://steamcommunity.com/app/1263610</storeLink>
		</game>
		<game>
			<appID>927990</appID>
			<name>A Game About</name>
			<logo>https://cdn.cloudflare.steamstatic.com/steam/apps/927990/capsule_184x69.jpg?t=1572500514</logo>
			<storeLink>https://steamcommunity.com/app/927990</storeLink>
			<statsLink>https://steamcommunity.com/id/impizzaman/stats/927990</statsLink>
			<globalStatsLink>https://steamcommunity.com/stats/927990/achievements/</globalStatsLink>
		</game>
		<game>
			<appID>2055490</appID>
			<name>A Game with a Kitty 1 &amp; 2</name>
			<logo>https://cdn.cloudflare.steamstatic.com/steam/apps/2055490/capsule_184x69.jpg?t=1656438869</logo>
			<storeLink>https://steamcommunity.com/app/2055490</storeLink>
		</game>
		<game>
			<appID>848340</appID>
			<name>AGE</name>
			<logo>https://cdn.cloudflare.steamstatic.com/steam/apps/848340/capsule_184x69.jpg?t=1677274477</logo>
			<storeLink>https://steamcommunity.com/app/848340</storeLink>
		</game>
		<game>
			<appID>2174620</appID>
			<name>Agelast</name>
			<logo>https://cdn.cloudflare.steamstatic.com/steam/apps/2174620/capsule_184x69.jpg?t=1668336429</logo>
			<storeLink>https://steamcommunity.com/app/2174620</storeLink>
		</game>
		<game>
			<appID>1299580</appID>
			<name>Agent-00</name>
			<logo>https://cdn.cloudflare.steamstatic.com/steam/apps/1299580/capsule_184x69.jpg?t=1590923664</logo>
			<storeLink>https://steamcommunity.com/app/1299580</storeLink>
			<statsLink>https://steamcommunity.com/id/impizzaman/stats/1299580</statsLink>
			<globalStatsLink>https://steamcommunity.com/stats/1299580/achievements/</globalStatsLink>
		</game>
		<game>
			<appID>1486270</appID>
			<name>Agent of Chaos</name>
			<logo>https://cdn.cloudflare.steamstatic.com/steam/apps/1486270/capsule_184x69.jpg?t=1608624062</logo>
			<storeLink>https://steamcommunity.com/app/1486270</storeLink>
		</game>
		<game>
			<appID>1013830</appID>
			<name>Agent Of Love</name>
			<logo>https://cdn.cloudflare.steamstatic.com/steam/apps/1013830/capsule_184x69.jpg?t=1612650198</logo>
			<storeLink>https://steamcommunity.com/app/1013830</storeLink>
		</game>
		<game>
			<appID>2233980</appID>
			<name>Agent Team Simulator</name>
			<logo>https://cdn.cloudflare.steamstatic.com/steam/apps/2233980/capsule_184x69.jpg?t=1687444239</logo>
			<storeLink>https://steamcommunity.com/app/2233980</storeLink>
			<statsLink>https://steamcommunity.com/id/impizzaman/stats/2233980</statsLink>
			<globalStatsLink>https://steamcommunity.com/stats/2233980/achievements/</globalStatsLink>
		</game>
		<game>
			<appID>17510</appID>
			<name>Age of Chivalry</name>
			<logo>https://cdn.cloudflare.steamstatic.com/steam/apps/17510/capsule_184x69.jpg?t=1577355178</logo>
			<storeLink>https://steamcommunity.com/app/17510</storeLink>
			<hoursOnRecord>0.4</hoursOnRecord>
			<statsLink>https://steamcommunity.com/id/impizzaman/stats/AgeOfChivalry</statsLink>
			<globalStatsLink>https://steamcommunity.com/stats/AgeOfChivalry/achievements/</globalStatsLink>
		</game>
		<game>
			<appID>933110</appID>
			<name>Age of Empires III: Definitive Edition</name>
			<logo>https://cdn.cloudflare.steamstatic.com/steam/apps/933110/capsule_184x69.jpg?t=1691530205</logo>
			<storeLink>https://steamcommunity.com/app/933110</storeLink>
			<statsLink>https://steamcommunity.com/id/impizzaman/stats/933110</statsLink>
			<globalStatsLink>https://steamcommunity.com/stats/933110/achievements/</globalStatsLink>
		</game>
		<game>
			<appID>882410</appID>
			<name>Age of Fear: The Free World</name>
			<logo>https://cdn.cloudflare.steamstatic.com/steam/apps/882410/capsule_184x69.jpg?t=1683125609</logo>
			<storeLink>https://steamcommunity.com/app/882410</storeLink>
			<statsLink>https://steamcommunity.com/id/impizzaman/stats/882410</statsLink>
			<globalStatsLink>https://steamcommunity.com/stats/882410/achievements/</globalStatsLink>
		</game>
		</games></gamesList>